winsay/__init__.py
winsay/winsay.py
winsay-1.1.1.dist-info/LICENSE
winsay-1.1.1.dist-info/METADATA
winsay-1.1.1.dist-info/WHEEL
winsay-1.1.1.dist-info/entry_points.txt
winsay-1.1.1.dist-info/top_level.txt
winsay-1.1.1.dist-info/RECORD
