Metadata-Version: 2.1
Name: winsay
Version: 1.1.1
Summary: say in windows
Home-page: https://github.com/sukhbinder/winsay
Author: sukhbinder
Author-email: sukh2010@yahoo.com
License: Private
Keywords: say,windows,mac,computer,speak
Classifier: License :: OSI Approved :: MIT License
Classifier: Programming Language :: Python :: 3
Classifier: Programming Language :: Python :: 3.7
License-File: LICENSE
Requires-Dist: pywin32
Provides-Extra: test
Requires-Dist: pytest ; extra == 'test'
